_pygptj.cpython-310-i386-linux-gnu.so
pygptj/__init__.py
pygptj/cli.py
pygptj/model.py
pygptj/_logger.py
pygptj/constants.py
pygptj-2.0.3.dist-info/METADATA
pygptj-2.0.3.dist-info/entry_points.txt
pygptj-2.0.3.dist-info/top_level.txt
pygptj-2.0.3.dist-info/RECORD
pygptj-2.0.3.dist-info/WHEEL
pygptj-2.0.3.dist-info/LICENSE
