Metadata-Version: 2.1
Name: pygptj
Version: 2.0.3
Summary: Python bindings for the GGML GPT-J Laguage model
Author: Abdeladim Sadiki
License: MIT
Project-URL: Documentation, https://abdeladim-s.github.io/pygptj
Project-URL: Source, https://github.com/abdeladim-s/pygptj
Project-URL: Tracker, https://github.com/abdeladim-s/pygptj/issues
Requires-Python: >=3.8
License-File: LICENSE
